{
  "type": "FeatureCollection",
  "features": [
    {
      "type": "Feature",
      "properties": {
        "a": "Aceh",
        "b": "Lampung",
        "location": "route"
      },
      "geometry": {
        "type": "LineString",
        "coordinates": [
          [
            96.17275398575825,
            3.22597710753758
          ],
          [
            96.74421337502044,
            2.611416231030153
          ],
          [
            96.9859846550929,
            1.9306616268787276
          ],
          [
            97.5354648370758,
            1.732967848190013
          ],
          [
            98.15088264089663,
            1.2276621841741453
          ],
          [
            98.41463312824845,
            0.502501514441385
          ],
          [
            97.93109056810347,
            -0.26669369160363715
          ],
          [
            99.22786379758308,
            -0.7062211207912588
          ],
          [
            99.82130239412461,
            -1.277540785681675
          ],
          [
            100.3488033688282,
            -2.287990331067335
          ],
          [
            101.22797166000085,
            -3.582917061326973
          ],
          [
            101.66755580558714,
            -4.196858556199665
          ],
          [
            102.5687033040391,
            -4.72271286133498
          ]
        ]
      }
    },
    {
      "type": "Feature",
      "properties": {
        "location": "bounding-rectangle"
      },
      "geometry": {
        "type": "Polygon",
        "coordinates": [
          [
            [
              95.00732209106526,
              -5.185266091383039
            ],
            [
              105.85601625000521,
              -5.185266091383039
            ],
            [
              105.85601625000521,
              5.611439998954922
            ],
            [
              95.00732209106526,
              5.611439998954922
            ],
            [
              95.00732209106526,
              -5.185266091383039
            ]
          ]
        ]
      }
    }
  ]
}